nazo_rand/__init__.py
nazo_rand/nazo_rand.cpp
nazo_rand/nazo_rand.cpython-310-x86_64-linux-gnu.so
nazo_rand/nazo_rand.hpp
nazo_rand/nazo_rand.pxd
nazo_rand/nazo_rand.pyi
nazo_rand/nazo_rand.pyx
nazo_rand-0.1.1.dist-info/LICENSE
nazo_rand-0.1.1.dist-info/METADATA
nazo_rand-0.1.1.dist-info/WHEEL
nazo_rand-0.1.1.dist-info/top_level.txt
nazo_rand-0.1.1.dist-info/RECORD
